Metadata-Version: 2.2
Name: inline_reference
Version: 1.0.0
Summary: Sphinx extension for creating cross-reference links to arbitrary inline text
Author-email: Rastislav Turanyi <rastislav.turanyi@stfc.ac.uk>
Maintainer-email: Rastislav Turanyi <rastislav.turanyi@stfc.ac.uk>
License:                     GNU GENERAL PUBLIC LICENSE
Project-URL: Repository, https://github.com/pace-neutrons/inline_reference
Project-URL: Documentation, https://pace-neutrons.github.io/inline_reference/
Project-URL: Homepage, https://pace-neutrons.github.io/inline_reference/
Project-URL: Issues, https://github.com/pace-neutrons/inline_reference/issues
Keywords: Python,docs,documentation,sphinx,sphinx-extension,inline cross-reference,inline reference
Classifier: Development Status :: 5 - Production/Stable
Classifier: Framework :: Sphinx :: Domain
Classifier: Framework :: Sphinx :: Extension
Classifier: Intended Audience :: Developers
Classifier: License :: OSI Approved :: GNU General Public License v3 (GPLv3)
Classifier: Operating System :: OS Independent
Classifier: Programming Language :: Python
Classifier: Topic :: Documentation :: Sphinx
License-File: LICENSE
Requires-Dist: sphinx>=6.0.0
Provides-Extra: test
Requires-Dist: pytest>=8.3.2; extra == "test"
Provides-Extra: docs
Requires-Dist: sphinx_rtd_theme>=3.0.2; extra == "docs"
Requires-Dist: numpydoc>=1.8.0; extra == "docs"
